greeng3_python/__init__.py
greeng3_python/algorithms/__init__.py
greeng3_python/algorithms/levenshtein.py
greeng3_python/algorithms/logic.py
greeng3_python/algorithms/repriority_queue.py
greeng3_python/algorithms/union_find.py
greeng3_python/algorithms/voronoi.py
greeng3_python/content/__init__.py
greeng3_python/content/epub_to_txt.py
greeng3_python/content/pdf.py
greeng3_python/curation/__init__.py
greeng3_python/curation/dir_data.py
greeng3_python/curation/dir_json.py
greeng3_python/curation/dir_ops.py
greeng3_python/date_time/__init__.py
greeng3_python/date_time/zeller.py
greeng3_python/decorators/__init__.py
greeng3_python/decorators/arg_checking_example.py
greeng3_python/decorators/caching_example.py
greeng3_python/decorators/context_example.py
greeng3_python/decorators/generic.py
greeng3_python/decorators/proxy_example.py
greeng3_python/diffs/__init__.py
greeng3_python/diffs/visual.py
greeng3_python/docker/__init__.py
greeng3_python/docker/image.py
greeng3_python/filesystem/__init__.py
greeng3_python/filesystem/partition_filenames.py
greeng3_python/filesystem/paths.py
greeng3_python/isbn/__init__.py
greeng3_python/isbn/isbn.py
greeng3_python/isbn/isbndb.py
greeng3_python/isbn/title_isbn.py
greeng3_python/k8s/__init__.py
greeng3_python/k8s/secrets.py
greeng3_python/language/__init__.py
greeng3_python/language/alphabet.py
greeng3_python/language/bumper_sticker.py
greeng3_python/language/periodic_table.py
greeng3_python/math/__init__.py
greeng3_python/math/numeric_by_ref.py
greeng3_python/math/primes.py
greeng3_python/process/__init__.py
greeng3_python/process/interprocess_lock.py
greeng3_python/strings/__init__.py
greeng3_python/strings/affix.py
greeng3_python/utils/__init__.py
greeng3_python/utils/compare.py
greeng3_python/utils/key_functions.py
tests/__init__.py
tests/test_skeleton.py
tests/k8s/__init__.py
greeng3_python-0.1.9.dist-info/METADATA
greeng3_python-0.1.9.dist-info/WHEEL
greeng3_python-0.1.9.dist-info/top_level.txt
greeng3_python-0.1.9.dist-info/RECORD
