Metadata-Version: 2.1
Name: greeng3-python
Version: 0.1.9
Summary: A library of things I find useful.
Home-page: https://gitlab.com/greeng3/greeng3_python
Author: Gordon Greene
Author-email: greeng3@obscure-reference.com
License: MIT
Classifier: Programming Language :: Python :: 3
Classifier: License :: OSI Approved :: MIT License
Classifier: Operating System :: OS Independent
Requires-Python: >=3.11
Requires-Dist: bs4
Requires-Dist: docker
Requires-Dist: ebooklib
Requires-Dist: multipledispatch
Requires-Dist: nltk
Requires-Dist: pydantic
Requires-Dist: requests
